daruma/__init__.py
daruma/daruma_module.py
daruma/functions.py
daruma/models.py
daruma/data/AAindex553-Normal-X0.feature
daruma/data/CNN3_128_9_NN2_121_128.weight
daruma-0.2.0.dist-info/METADATA
daruma-0.2.0.dist-info/WHEEL
daruma-0.2.0.dist-info/entry_points.txt
daruma-0.2.0.dist-info/top_level.txt
daruma-0.2.0.dist-info/RECORD
